jp_flowchartjs/__init__.py
jp_flowchartjs/jp_flowchartjs.py
jp_flowchartjs-0.0.1.dist-info/LICENSE
jp_flowchartjs-0.0.1.dist-info/METADATA
jp_flowchartjs-0.0.1.dist-info/WHEEL
jp_flowchartjs-0.0.1.dist-info/top_level.txt
jp_flowchartjs-0.0.1.dist-info/RECORD
