Metadata-Version: 2.1
Name: jp-flowchartjs
Version: 0.0.1
Summary: IPython/Jupyter notebook magic for generating JS flowcharts.
Home-page: https://github.com/innovationOUtside/flowchart_js_jp_proxy_widget
Author: Tony Hirst
Author-email: tony.hirst@open.ac.uk
License: MIT License
Platform: UNKNOWN
Classifier: Development Status :: 3 - Alpha
Classifier: Environment :: Web Environment
Classifier: Intended Audience :: Education
Classifier: License :: Free For Educational Use
Classifier: Programming Language :: Python :: 3.6
Classifier: Programming Language :: Python :: 3.7
Classifier: Topic :: Education
Classifier: Topic :: Scientific/Engineering :: Visualization
Requires-Dist: jp-proxy-widget
Requires-Dist: cairosvg
